simple/__init__.py
simple/czsc/CzscModelEngine.py
simple/czsc/CzscModelEngineFenbi.py
simple/czsc/CzscModelEngineFenxing.py
simple/czsc/CzscModelEngineHebing.py
simple/czsc/CzscModelEngineXianduan.py
simple/czsc/CzscModelEngineZhongshu.py
simple/czsc/CzscModelEngineZhongshuXd.py
simple/czsc/CzscRealtimeModelEngineFenbi.py
simple/czsc/CzscRealtimeModelEngineXianduan.py
simple/czsc/CzscRealtimeModelEngineZhongshu.py
simple/czsc/Utils.py
simple/czsc/__init__.py
simple/draw/HtmlAutoFit.py
simple/draw/KdrawGrid.py
simple/draw/KdrawRealtimeMultiPeriod.py
simple/draw/__init__.py
simple/factor/FactorAbstract.py
simple/factor/Macd.py
simple/factor/XianduanSanmai.py
simple/factor/__init__.py
simple/logger/__init__.py
simple/logger/logger.py
simple/pusher/__init__.py
simple/pusher/serverj.py
simple_czsc-0.1.1.dist-info/LICENSE
simple_czsc-0.1.1.dist-info/METADATA
simple_czsc-0.1.1.dist-info/WHEEL
simple_czsc-0.1.1.dist-info/top_level.txt
simple_czsc-0.1.1.dist-info/RECORD
