Metadata-Version: 2.1
Name: simple-czsc
Version: 0.1.1
Summary: 缠论量化工具集
Home-page: https://github.com/simple-trade/simple-czsc
Author: simple-trade
Author-email: simple_czsc@163.com
License: MIT
Platform: UNKNOWN
Classifier: License :: OSI Approved :: MIT License
Classifier: Programming Language :: Python
Classifier: Programming Language :: Python :: 3
Classifier: Programming Language :: Python :: 3.6
Classifier: Programming Language :: Python :: 3.7
Classifier: Programming Language :: Python :: Implementation :: CPython
Classifier: Programming Language :: Python :: Implementation :: PyPy
Requires-Python: >=3.6.0
License-File: LICENSE
Requires-Dist: numpy
Requires-Dist: pandas
Requires-Dist: pyecharts
Requires-Dist: requests
Requires-Dist: selenium
Requires-Dist: snapshot-selenium
Requires-Dist: TA-Lib
